DA_3/design.sv
// EEM16 - Logic Design
// 2018_05_01
// Design Assignment #3 
// dassign3.v

// Motor Controller 
// Produces the proper motor_drv pulse sequence
// Sample code from Design Assignment #2 for your reference. 
// You can choose to modify this to your design if you so choose.
module motor_ctrl (motor_drv, done, forw, rev, reset, drv_clk);
  output [3:0] motor_drv;
  output 	done;
  input 	forw, rev, reset, drv_clk;
  // Parameters declaration
  parameter P0_ST = 2'b00;
  parameter P1_ST = 2'b01;
  parameter P2_ST = 2'b10;
  parameter P3_ST = 2'b11;
  
  reg [1:0] state, nx_state;
  reg done;
  reg [3:0] motor_drv;

  always @(posedge drv_clk) begin
    state <= nx_state;
  end
  
  always @(state or forw or rev or reset) begin
    if (reset) begin
      nx_state = P0_ST;
      motor_drv = 4'b0000;
      done = 0;
    end
    else begin
      if (forw == 1'b1) begin
        case (state)
          P0_ST: begin
            nx_state = P1_ST;
            motor_drv = 4'b0001;
            done = 1'b1;
          end
          P1_ST: begin
            nx_state = P2_ST;
            motor_drv = 4'b0010;
            done = 1'b0;
          end
          P2_ST: begin
            nx_state = P3_ST;
            motor_drv = 4'b0100;
            done = 1'b0;
          end
          P3_ST: begin
            nx_state = P0_ST;
            motor_drv = 4'b1000;
            done = 1'b0;
          end
          default: begin
            nx_state = P0_ST;
            motor_drv = 4'b0000;
            done = 1'b0;
          end
        endcase // case (state)
      end // if (forw == 1'b1)
      else if (rev == 1'b1) begin
        case (state)
          P0_ST: begin
            nx_state = P3_ST;
            motor_drv = 4'b0001;
            done = 1'b1;
          end
          P1_ST: begin
            nx_state = P0_ST;
            motor_drv = 4'b0010;
            done = 1'b0;
          end
          P2_ST: begin
            nx_state = P1_ST;
            motor_drv = 4'b0100;
            done = 1'b0;
          end
          P3_ST: begin
            nx_state = P2_ST;
            motor_drv = 4'b1000;
            done = 1'b0;
          end
          default: begin
            nx_state = P0_ST;
            motor_drv = 4'b0000;
            done = 1'b0;
          end
        endcase // case (state)
      end // if (rev == 1'b1)
      else begin
        nx_state = state;
        motor_drv = 4'b0000;
        done = 1'b0;
      end
    end // else: !if(reset)
  end // always @ (state or forw or rev or reset)
endmodule
// ASCII to Letter Dial Position 
// Converts the 7-bit ASCII to the proper position location from 0-31. 
// Sample code from Design Assignment #1 for your reference. 
// You can choose to modify this to your design if you so choose.
module ascii2pos(pos, ascii);
   output [4:0] pos;
   reg [4:0] 	pos;
   input [6:0] 	ascii;
   always @(ascii) begin
      case (ascii)
        7'b010_0000: pos[4:0] = 5'b00000;
        7'b110_0001: pos[4:0] = 5'b00001;
        7'b110_0010: pos[4:0] = 5'b00010;
        7'b110_0011: pos[4:0] = 5'b00011;
        7'b110_0100: pos[4:0] = 5'b00100;
        7'b110_0101: pos[4:0] = 5'b00101;
        7'b110_0110: pos[4:0] = 5'b00110;
        7'b110_0111: pos[4:0] = 5'b00111;
        7'b110_1000: pos[4:0] = 5'b01000;
        7'b110_1001: pos[4:0] = 5'b01001;
        7'b110_1010: pos[4:0] = 5'b01010;
        7'b110_1011: pos[4:0] = 5'b01011;
        7'b110_1100: pos[4:0] = 5'b01100;
        7'b110_1101: pos[4:0] = 5'b01101;
        7'b110_1110: pos[4:0] = 5'b01110;
        7'b110_1111: pos[4:0] = 5'b01111;
        7'b111_0000: pos[4:0] = 5'b10000;
        7'b111_0001: pos[4:0] = 5'b10001;
        7'b111_0010: pos[4:0] = 5'b10010;
        7'b111_0011: pos[4:0] = 5'b10011;
        7'b111_0100: pos[4:0] = 5'b10100;
        7'b111_0101: pos[4:0] = 5'b10101;
        7'b111_0110: pos[4:0] = 5'b10110;
        7'b111_0111: pos[4:0] = 5'b10111;
        7'b111_1000: pos[4:0] = 5'b11000;
        7'b111_1001: pos[4:0] = 5'b11001;
        7'b111_1010: pos[4:0] = 5'b11010;
        7'b010_1100: pos[4:0] = 5'b11101;
        7'b010_1110: pos[4:0] = 5'b11110;
        7'b011_1111: pos[4:0] = 5'b11111;
        default: pos[4:0] = 5'b00000;
      endcase // case (ascii)
   end // always @ (ascii)
endmodule 


// vvv--- Add any modules you need below---vvv
module count(stepCT, nextST, outDir, pos, prevST, dirI,req,reset);
  output [7:0]	stepCT;
  input req;
  output [4:0]	nextST;
  output [1:0] outDir;
  input [4:0]	pos;
  input [4:0] prevST;
  input [1:0] dirI;
  input reset;
  
  reg [4:0] i;
  reg [4:0] nextST;
  reg [7:0] stepCT;
  reg [1:0] outDir;

  always @(posedge req or reset) begin
    stepCT = 8'b00000000;
    if(reset) begin
      nextST = 5'b00000;
      stepCT = 0;
      outDir = 2;
    end
    else if(req) begin

      
      if (prevST < pos) begin
        
        if((pos - prevST) < (8+8)) begin//for is shortest path
          i = prevST;
          while (i < pos) begin
          	if (i % 4 == 3) begin
          	stepCT = stepCT + 7;
            end 
            else begin
            stepCT = stepCT + 6;
            end
            i = i + 1;
          end      
        outDir =  1;
        nextST = pos;
        end
        
        else begin//backwards is shortest path
          i = pos;
          while(i != prevST) begin
          if (i % 4 == 3) begin
            stepCT = stepCT + 7;
          end
          else begin
            stepCT = stepCT + 6;
          end
            i = i+ 1;
          end
        outDir = 0;
        nextST = pos; 
          
        end
        
      end // end if
      else if(prevST == pos) begin
        stepCT = 0;
        nextST = pos;
        outDir = 2;
          
      end // end if
      else begin // it already is at the next state it wants to move to

        if((prevST - pos) < (8+8)) begin //backwards is shortest path
          i = pos;
          while(i < prevST) begin
          if (i % 4 == 3) begin
            stepCT = stepCT + 7;
          end
          else begin
            stepCT = stepCT + 6;
          end
            i = i+1;
          end

        outDir = 0;
        nextST = pos;
        end
        
        else begin//for is shortest path
          i = prevST;
          while (i!= pos) begin
          if (i % 4 == 3) begin
            stepCT = stepCT + 7;
          end
          else begin
            stepCT = stepCT + 6;
          end
            i = i + 1;
          end

        outDir =  1;
        nextST = pos;  
        end
      end

    end
  end // always @ (*)
endmodule


// Main Module
module dassign3(ready, motor_drv, req, ascii_in, sys_clk, reset);
  output 		ready;
  output [3:0]	motor_drv;
  input 		req;
  input [6:0] 	ascii_in;
  input 		sys_clk, reset;
  // Instantiate the motor clock divider
  wire			motor_clk;
  
  motor_clk_div	mclkdiv(motor_clk, sys_clk, reset);
  // assign motor_clk = sys_clk;

  // Instantiate the motor control
  wire			motor_0001;
  wire			motor_forw, motor_rev;
  motor_ctrl 	mctl(motor_drv, motor_0001, motor_forw, motor_rev, reset, motor_clk);
  
  // Instantiate the ascii-to-position mapping
  wire [4:0] 	pos;
  reg [4:0] next_pos;
  ascii2pos		a2p(pos, ascii_in);    

  always @(pos) begin
    next_pos<=pos;
  end
  // Instantiate any additional modules you need
  count	ctr(count, prvST, dir, next_pos, nextST, outDir, req, reset);
  // Declare your variables
  wire [7:0]	count;
  reg [7:0]		count2;
  wire [4:0]	prvST;
  reg [4:0]		nextST;
  wire [1:0] dir;
  reg [1:0] outDir;
  // Your code start below	
  always @(count or reset) begin
    if(reset) begin
      count2 <= count;
      nextST <= 0;
      outDir <= 2;
    end
    else if (count >= 0) begin 
      count2 <= count;
      nextST <= prvST;
      outDir <= dir;
    end
  end
  
  always @(ascii_in) begin
    count2 <= count;
  end
  
  always @(posedge sys_clk) begin
    // Storage Elements
    if (reset) begin
      nextST = 0;
      outDir = 1;
    end
    if (ready) begin
      count2 = count;
    end
  end
  
  always @(posedge motor_clk) begin
    // Combinational Logic Elements
    if ((count2 != 0) |( outDir != 2)) begin
      count2 = count2 - 1;
    end // if statement
  end
  
  assign ready = (count2 == 0);
  assign motor_rev = (outDir == 0) & (ready != 1);
  assign motor_forw = outDir & (ready != 1);
  
endmodule

DA_3/testbench.sv
//--------------------------------------------------------------------
//		Timescale
//		Means that if you do #1 in the initial block of your
//		testbench, time is advanced by 1ns instead of 1ps
//--------------------------------------------------------------------
`timescale 1ns / 1ps
`define HCYC 100
`define CYC 200
//`define STRLEN 32
//`define STR "abcdefghijklmnopqrstuvwxyz.,?   "
`define STRLEN 28
`define STR "able was i? ere, i saw elba."

//--------------------------------------------------------------------
//		Design Assign #3, Testbench.
//--------------------------------------------------------------------
//
// Motor Model
// A pseudo model of the motor behavior
// **Do not modify**
//
module motor(count, err, motor_drv, drv_clk, reset);
   	output [7:0]    count;
   	output 	err;
   	input [3:0] 	motor_drv;
   	input 	drv_clk, reset;

   	reg signed [7:0] count;
   	reg 		err;
   	reg [3:0] 	prev_motor_drv;
   
   	always @(motor_drv or reset) begin
		if (reset) begin
	 		count = 0;
	 		prev_motor_drv=4'b0000;
      	end
      	else begin
	 		case (motor_drv)
	   		4'b0000: begin
	      		// $display("No Motor Drive: drv=%b prev_drv=%b", motor_drv, prev_motor_drv);
	   		end
	   		4'b0001: begin
	      		err = 0;
	      		if (prev_motor_drv == 4'b0010)
					count = count-1;
	      		else if (prev_motor_drv == 4'b1000)
					count = count+1;
	      		else if (prev_motor_drv == 4'b0001)
					;
	      		// $display("No Motor Change: drv=%b prev_drv=%b", motor_drv, prev_motor_drv);		
	      		else if (prev_motor_drv == 4'b0000)
					;
	      		// $display("From Reset: drv=%b prev_drv=%b", motor_drv, prev_motor_drv);		
	      		else begin
		 		// $display("ERR: drv=%b prev_drv=%b", motor_drv, prev_motor_drv);
		 			err = 1;
	      		end
	      		prev_motor_drv=4'b0001;
	   		end
	   		4'b0011: begin
	      		if ((prev_motor_drv!==4'b0001) || (prev_motor_drv!==4'b0010)) begin
		 		// $display("ERR: drv=%b prev_drv=%b", motor_drv, prev_motor_drv);
		 			err = 1;
	      		end
	   		end
	   		4'b0010: begin
	      		err = 0;
	      		if (prev_motor_drv == 4'b0100)
					count = count-1;
	      		else if (prev_motor_drv == 4'b0001)
					count = count+1;
	      		else if (prev_motor_drv == 4'b0010)
					;
  	     		// $display("No Motor Change: drv=%b prev_drv=%b", motor_drv, prev_motor_drv);		
	     		else begin
		 		// $display("ERR: drv=%b prev_drv=%b", motor_drv, prev_motor_drv);
		 			err = 1;
	      		end
	      		prev_motor_drv=4'b0010;	      		
	   		end
	   		4'b0110: begin
      	      	if ((prev_motor_drv!==4'b0100) || (prev_motor_drv!==4'b0010)) begin
		 		// $display("ERR: drv=%b prev_drv=%b", motor_drv, prev_motor_drv);
		 			err = 1;
	      		end
	   		end
	   		4'b0100: begin
	    		err = 0;
	      		if (prev_motor_drv == 4'b1000)
					count = count-1;
	      		else if (prev_motor_drv == 4'b0010)
					count = count+1;
	      		else if (prev_motor_drv == 4'b0100)
					;
	      		// $display("No Motor Change: drv=%b prev_drv=%b", motor_drv, prev_motor_drv);		
	      		else begin
		 		// $display("ERR: drv=%b prev_drv=%b", motor_drv, prev_motor_drv);
		 			err = 1;
	      		end
	      		prev_motor_drv=4'b0100; 			      		
	   		end
	   		4'b1100: begin
      	  		if ((prev_motor_drv!==4'b1000) || (prev_motor_drv!==4'b0001)) begin
		 	  	// $display("ERR: drv=%b prev_drv=%b", motor_drv, prev_motor_drv);
		 			err = 1;
	      		end
	   		end
	   		4'b1000: begin
	      		err = 0;
	      		if (prev_motor_drv == 4'b0001)
					count = count-1;
	      		else if (prev_motor_drv == 4'b0100)
					count = count+1;
	      		else if (prev_motor_drv == 4'b1000)
					;
	      		// $display("No Change: drv=%b prev_drv=%b", motor_drv, prev_motor_drv);		
	      		else begin
		 		// $display("ERR: drv=%b prev_drv=%b", motor_drv, prev_motor_drv);
		 			err = 1;
	      		end
	      		prev_motor_drv=4'b1000; 		
	   		end
	   		4'b1001: begin
      	      	if ((prev_motor_drv!==4'b1000) || (prev_motor_drv!==4'b0001)) begin
		 		// $display("ERR: drv=%b prev_drv=%b", motor_drv, prev_motor_drv);
		 			err = 1;
	      		end
	   		end
	   		default: begin
	      		// $display("ERR: drv=%b prev_drv=%b", motor_drv, prev_motor_drv);
	      		err = 1;	      
	   		end
	 		endcase // case (motor_drv)
	      	if (count > 99)
	      		count = count - 200;
			else if (count < -100)
      			count = count + 200;	      			      			 		
      	end // else: !if(reset)
   	end // always @ (motor_drv or reset)
endmodule // motor
//
// Clock Divider 
// Produces a motor clock that is 1/16th the frequency of the system clock
//    local parameter define_speed is set to 8.
// 
module motor_clk_div(
       output reg clk_out,
       input clk_in,
       input reset
    );
    
    localparam define_speed = 26'd8;
    
    reg [25:0] count;
    
    // Run on the positive edge of the clk and rst signals
    always @ (posedge clk_in or reset)
    begin
        // When rst is high set count and new_clk to 0
        if (reset == 1'b1)
        begin 
            count = 26'b0;   
            clk_out = 1'b0;            
        end
        // When the count has reached the target constant
        else if (count == define_speed)
        begin
            count = 26'b0;
            clk_out = ~clk_out;
        end
        // increment the clock and keep the output clock
        // the same when the target constant hasn't been reached        
        else
        begin
            count = count + 1'b1;
            clk_out = clk_out;
        end
    end
endmodule
//
// Clock Generator
// Generates the system clock for the Letter Dial Controller
// **Do not modify**
//
module clkgen(clk);
   output clk;

   reg 	  clk;
   
   initial
     clk = 1'b0;
   always
     #(`HCYC) clk=~clk;
endmodule
//
// Motor Step to ASCII
// Converts the -100 to 99 values of the motor step into what the ASCII values should be
// This checks within a window for each character. 
//
module mstep2ascii(pos_char, motor_stp_cnt);
	output 	[7:0] 		pos_char;
	input signed [7:0] 	motor_stp_cnt;
	
	reg 	[7:0] 		pos_char;
	
	always @(*) begin
    	if ((motor_stp_cnt > -3) && (motor_stp_cnt <= 3))
    	    pos_char = 8'b0010_0000;
    	else if ((motor_stp_cnt > 3) && (motor_stp_cnt <= 9))
    		pos_char = 8'b0110_0001;
    	else if ((motor_stp_cnt > 9) && (motor_stp_cnt <= 15))
    		pos_char = 8'b0110_0010;
    	else if ((motor_stp_cnt > 15) && (motor_stp_cnt <= 21))
    		pos_char = 8'b0110_0011;
    	else if ((motor_stp_cnt > 21) && (motor_stp_cnt <= 28))
    		pos_char = 8'b0110_0100;
    	else if ((motor_stp_cnt > 28) && (motor_stp_cnt <= 34))
    		pos_char = 8'b0110_0101;
    	else if ((motor_stp_cnt > 34) && (motor_stp_cnt <= 40))
    		pos_char = 8'b0110_0110;
    	else if ((motor_stp_cnt > 40) && (motor_stp_cnt <= 46))
    		pos_char = 8'b0110_0111;
    	else if ((motor_stp_cnt > 46) && (motor_stp_cnt <= 53))
    		pos_char = 8'b0110_1000;
    	else if ((motor_stp_cnt > 53) && (motor_stp_cnt <= 59))
    		pos_char = 8'b0110_1001;
    	else if ((motor_stp_cnt > 59) && (motor_stp_cnt <= 65))
    		pos_char = 8'b0110_1010;
    	else if ((motor_stp_cnt > 65) && (motor_stp_cnt <= 71))
    		pos_char = 8'b0110_1011;
    	else if ((motor_stp_cnt > 71) && (motor_stp_cnt <= 78))
    		pos_char = 8'b0110_1100;
    	else if ((motor_stp_cnt > 78) && (motor_stp_cnt <= 84))
    		pos_char = 8'b0110_1101;
    	else if ((motor_stp_cnt > 84) && (motor_stp_cnt <= 90))
    		pos_char = 8'b0110_1110;
    	else if ((motor_stp_cnt > 90) && (motor_stp_cnt <= 96))
    		pos_char = 8'b0110_1111;
    	else if (((motor_stp_cnt > 96) && (motor_stp_cnt <= 99)) || ((motor_stp_cnt > -100) && (motor_stp_cnt <= -97)))
    		pos_char = 8'b0111_0000;
    	else if ((motor_stp_cnt > -97) && (motor_stp_cnt <= -91))
    		pos_char = 8'b0111_0001;
    	else if ((motor_stp_cnt > -91) && (motor_stp_cnt <= -85))
    		pos_char = 8'b0111_0010;
    	else if ((motor_stp_cnt > -85) && (motor_stp_cnt <= -78))
    		pos_char = 8'b0111_0011;
    	else if ((motor_stp_cnt > -78) && (motor_stp_cnt <= -72))
    		pos_char = 8'b0111_0100;
    	else if ((motor_stp_cnt > -72) && (motor_stp_cnt <= -66))
    		pos_char = 8'b0111_0101;
    	else if ((motor_stp_cnt > -66) && (motor_stp_cnt <= -60))
    		pos_char = 8'b0111_0110;
    	else if ((motor_stp_cnt > -60) && (motor_stp_cnt <= -53))
    		pos_char = 8'b0111_0111;
    	else if ((motor_stp_cnt > -53) && (motor_stp_cnt <= -47))
    		pos_char = 8'b0111_1000;
    	else if ((motor_stp_cnt > -47) && (motor_stp_cnt <= -41))
    		pos_char = 8'b0111_1001;
    	else if ((motor_stp_cnt > -41) && (motor_stp_cnt <= -35))
    		pos_char = 8'b0111_1010;
    	else if ((motor_stp_cnt > -35) && (motor_stp_cnt <= -28))
    		pos_char = 8'b0010_0000; //sp
    	else if ((motor_stp_cnt > -28) && (motor_stp_cnt <= -22))
    		pos_char = 8'b0010_0000; //sp
    	else if ((motor_stp_cnt > -22) && (motor_stp_cnt <= -16))
    		pos_char = 8'b0010_1100; //,
    	else if ((motor_stp_cnt > -16) && (motor_stp_cnt <= -10))
    		pos_char = 8'b0010_1110; //.
    	else if ((motor_stp_cnt > -10) && (motor_stp_cnt <= -3))
    		pos_char = 8'b0011_1111; //?
 		else begin
			pos_char = 8'b0010_0000; //sp
			$display("Error: step count: %d", motor_stp_cnt);
    	end
	end
endmodule

module dassign3_tb();
   	//----------------------------------------------------------------
   	//		Test Bench Signal Declarations
   	//----------------------------------------------------------------
   	integer i,j,outfile;
	
   	reg [4:0] pos_mem[0:255];
   	reg [7:0] pos_char;
   	reg [255:0] str;
   	reg [4:0]   tb_pos;
   
   	//----------------------------------------------------------------
   	//		Instantiate modules Module
   	//----------------------------------------------------------------
   	wire signed [7:0] 	motor_stp_cnt;
	wire 		[7:0] 	dut_pos_char;

   	clkgen 	clkgen_1(sys_clk);
   	motor 	motor_1(motor_stp_cnt, step_err, motor_drv, sys_clk, reset);
   	mstep2ascii	m2a(dut_pos_char, motor_stp_cnt);
   	dassign3 letterdial(ready, motor_drv, req, ascii_in, sys_clk, reset);
   
   	//----------------------------------------------------------------
   	//		Design Task Signal Declarations
   	//----------------------------------------------------------------
   	wire [3:0] 	motor_drv;
   	wire       	done, sys_clk;
   
   	reg 	      	reset;
   	reg 	[6:0]	ascii_in;
   	reg			req;

   	wire       step_err;
      
   	//----------------------------------------------------------------
   	//		Test Stimulus
   	//----------------------------------------------------------------
   	initial begin
    	outfile=$fopen("dassign3.txt");
      	if(!outfile) begin
	 		$display("FAIL WRITE FILE");
	 		$finish;
      	end
      	$dumpfile("dassign3.vcd");
      	$dumpvars(0,dassign3_tb);
      	$readmemb("./ascii_pos.txt", pos_mem);
      	str = `STR;
	    #`CYC 	
	    	reset = 0;
	    	req = 0;
	    #`CYC	reset = 1;
	    #(2*`CYC) reset = 0;
	    #`CYC	
   		for(i=`STRLEN-1;i>=0;i=i-1) begin
      		for(j=0;j<8;j=j+1)
			pos_char[j] = str[8*i+j];
     		ascii_in = pos_char[6:0];
      		tb_pos = pos_mem[pos_char];
      		wait (ready==1)
      		#(1.5*`CYC) ;
      			req = 1;
      		$display("new ready: %b, req: %b, pos_char: %b, pos: %b", ready, req, pos_char, tb_pos);
      		#`CYC ;
      			req = 0;
      		#`HCYC ;
      		$display("ready: %b, req: %b, pos_char: %b, pos: %b", ready, req, pos_char, tb_pos);
		end	
		wait (ready == 1)
  		#(10*`CYC) ;
		$finish;			 
   	end

   	reg [7:0] tb_pos_char;
   	
   	always @(req) begin
		if (req == 1) begin
			tb_pos_char = pos_char;
			$display("Req==1: Time: %d", $time);
			#`HCYC ;
			wait (ready == 1)
			$display("Ready==1: Time: %d", $time);
			if (dut_pos_char == tb_pos_char) begin
				$display("Correct!\treq: %c\tresponse: %c\tmotor_step: %d\ttime:%d", 
					tb_pos_char, dut_pos_char, motor_stp_cnt,$time);
			end
			else begin
				$display("Incorrect!\treq: %c\tresponse: %c\tmotor_step: %d\ttime:%d",
					tb_pos_char, dut_pos_char, motor_stp_cnt,$time);
			end
		end
	end
	
	always @(dut_pos_char) begin
		$display("Passing through %c to reach TestBench Char: %c @ %d ", dut_pos_char, tb_pos_char, $time);
   	end

endmodule // dassign3_tb

DA_3/dassign3.vcd
$date
	Thu Jun  7 23:54:00 2018
$end
$version
	Icarus Verilog
$end
$timescale
	1ps
$end
$scope module dassign3_tb $end
$var wire 8 ! dut_pos_char [7:0] $end
$var wire 4 " motor_drv [3:0] $end
$var wire 8 # motor_stp_cnt [7:0] $end
$var wire 1 $ ready $end
$var wire 1 % step_err $end
$var wire 1 & sys_clk $end
$var reg 7 ' ascii_in [6:0] $end
$var integer 32 ( i [31:0] $end
$var integer 32 ) j [31:0] $end
$var integer 32 * outfile [31:0] $end
$var reg 8 + pos_char [7:0] $end
$var reg 1 , req $end
$var reg 1 - reset $end
$var reg 256 . str [255:0] $end
$var reg 5 / tb_pos [4:0] $end
$var reg 8 0 tb_pos_char [7:0] $end
$scope module clkgen_1 $end
$var reg 1 1 clk $end
$upscope $end
$scope module motor_1 $end
$var wire 1 & drv_clk $end
$var wire 4 2 motor_drv [3:0] $end
$var wire 1 3 reset $end
$var reg 8 4 count [7:0] $end
$var reg 1 5 err $end
$var reg 4 6 prev_motor_drv [3:0] $end
$upscope $end
$scope module m2a $end
$var wire 8 7 motor_stp_cnt [7:0] $end
$var reg 8 8 pos_char [7:0] $end
$upscope $end
$scope module letterdial $end
$var wire 7 9 ascii_in [6:0] $end
$var wire 8 : count [7:0] $end
$var wire 2 ; dir [1:0] $end
$var wire 1 < motor_0001 $end
$var wire 1 = motor_clk $end
$var wire 4 > motor_drv [3:0] $end
$var wire 1 ? motor_forw $end
$var wire 1 @ motor_rev $end
$var wire 5 A pos [4:0] $end
$var wire 5 B prvST [4:0] $end
$var wire 1 $ ready $end
$var wire 1 C req $end
$var wire 1 3 reset $end
$var wire 1 & sys_clk $end
$var reg 8 D count2 [7:0] $end
$var reg 5 E nextST [4:0] $end
$var reg 5 F next_pos [4:0] $end
$var reg 2 G outDir [1:0] $end
$scope module mclkdiv $end
$var wire 1 & clk_in $end
$var wire 1 3 reset $end
$var reg 1 H clk_out $end
$var reg 26 I count [25:0] $end
$upscope $end
$scope module mctl $end
$var wire 1 = drv_clk $end
$var wire 1 ? forw $end
$var wire 1 3 reset $end
$var wire 1 @ rev $end
$var reg 1 J done $end
$var reg 4 K motor_drv [3:0] $end
$var reg 2 L nx_state [1:0] $end
$var reg 2 M state [1:0] $end
$upscope $end
$scope module a2p $end
$var wire 7 N ascii [6:0] $end
$var reg 5 O pos [4:0] $end
$upscope $end
$scope module ctr $end
$var wire 2 P dirI [1:0] $end
$var wire 5 Q pos [4:0] $end
$var wire 5 R prevST [4:0] $end
$var wire 1 C req $end
$var wire 1 3 reset $end
$var reg 5 S i [4:0] $end
$var reg 5 T nextST [4:0] $end
$var reg 2 U outDir [1:0] $end
$var reg 8 V stepCT [7:0] $end
$upscope $end
$upscope $end
$upscope $end
$enddefinitions $end
#0
$dumpvars
bx V
bx U
bx T
bx S
bx R
bx Q
bx P
bx O
bx N
bx M
bx L
b0 K
0J
bx I
xH
bx G
bx F
bx E
bx D
xC
bx B
bx A
x@
x?
b0 >
x=
0<
bx ;
bx :
bx 9
bx 8
bx 7
bx 6
x5
bx 4
x3
b0 2
01
bx 0
bx /
b1100001011000100110110001100101001000000111011101100001011100110010000001101001001111110010000001100101011100100110010100101100001000000110100100100000011100110110000101110111001000000110010101101100011000100110000100101110 .
x-
x,
bx +
b10 *
bx )
bx (
bx '
0&
x%
x$
bx #
b0 "
bx !
$end
#100000
11
1&
#200000
0?
0@
b0 D
1$
b0 V
b0 :
01
0&
0,
0C
0-
03
#300000
11
1&
#400000
b10 G
b10 P
b0 E
b0 R
b100000 8
b100000 !
b10 U
b10 ;
b0 T
b0 B
b0 L
0H
0=
b0 I
b0 6
b0 4
b0 #
b0 7
01
0&
1-
13
#500000
b1 G
b1 P
11
1&
#600000
01
0&
#700000
11
1&
#800000
b10 G
b10 P
bx L
b1 I
01
0&
0-
03
#900000
b10 I
11
1&
#1000000
b1 F
b1 Q
b1 O
b1 A
01
0&
b1 /
b1100001 '
b1100001 9
b1100001 N
b1100001 +
b1000 )
b11011 (
#1100000
b11 I
11
1&
#1200000
01
0&
#1300000
b0 L
1?
b1 G
b1 P
b1 E
b1 R
b100 I
b110 D
0$
b1 T
b1 B
b1 U
b1 ;
b110 V
b110 :
b1 S
b1100001 0
11
1&
1,
1C
#1400000
01
0&
#1500000
b101 I
11
1&
0,
0C
#1600000
b10 F
b10 Q
b10 O
b10 A
01
0&
b10 /
b1100010 '
b1100010 9
b1100010 N
b1100010 +
b1000 )
b11010 (
#1700000
b110 I
11
1&
#1800000
01
0&
#1900000
b111 I
11
1&
#2000000
01
0&
#2100000
b1000 I
11
1&
#2200000
01
0&
#2300000
b1 6
05
0%
1J
1<
b1 K
b1 "
b1 2
b1 >
b1 L
b0 M
b101 D
1H
1=
b0 I
11
1&
#2400000
01
0&
#2500000
b1 I
11
1&
#2600000
01
0&
#2700000
b10 I
11
1&
#2800000
01
0&
#2900000
b11 I
11
1&
#3000000
01
0&
#3100000
b100 I
11
1&
#3200000
01
0&
#3300000
b101 I
11
1&
#3400000
01
0&
#3500000
b110 I
11
1&
#3600000
01
0&
#3700000
b111 I
11
1&
#3800000
01
0&
#3900000
b1000 I
11
1&
#4000000
01
0&
#4100000
0H
0=
b0 I
11
1&
#4200000
01
0&
#4300000
b1 I
11
1&
#4400000
01
0&
#4500000
b10 I
11
1&
#4600000
01
0&
#4700000
b11 I
11
1&
#4800000
01
0&
#4900000
b100 I
11
1&
#5000000
01
0&
#5100000
b101 I
11
1&
#5200000
01
0&
#5300000
b110 I
11
1&
#5400000
01
0&
#5500000
b111 I
11
1&
#5600000
01
0&
#5700000
b1000 I
11
1&
#5800000
01
0&
#5900000
b10 6
b1 4
b1 #
b1 7
0J
0<
b10 K
b10 "
b10 2
b10 >
b10 L
b1 M
b100 D
1H
1=
b0 I
11
1&
#6000000
01
0&
#6100000
b1 I
11
1&
#6200000
01
0&
#6300000
b10 I
11
1&
#6400000
01
0&
#6500000
b11 I
11
1&
#6600000
01
0&
#6700000
b100 I
11
1&
#6800000
01
0&
#6900000
b101 I
11
1&
#7000000
01
0&
#7100000
b110 I
11
1&
#7200000
01
0&
#7300000
b111 I
11
1&
#7400000
01
0&
#7500000
b1000 I
11
1&
#7600000
01
0&
#7700000
0H
0=
b0 I
11
1&
#7800000
01
0&
#7900000
b1 I
11
1&
#8000000
01
0&
#8100000
b10 I
11
1&
#8200000
01
0&
#8300000
b11 I
11
1&
#8400000
01
0&
#8500000
b100 I
11
1&
#8600000
01
0&
#8700000
b101 I
11
1&
#8800000
01
0&
#8900000
b110 I
11
1&
#9000000
01
0&
#9100000
b111 I
11
1&
#9200000
01
0&
#9300000
b1000 I
11
1&
#9400000
01
0&
#9500000
b100 6
b10 4
b10 #
b10 7
b100 K
b100 "
b100 2
b100 >
b11 L
b10 M
b11 D
1H
1=
b0 I
11
1&
#9600000
01
0&
#9700000
b1 I
11
1&
#9800000
01
0&
#9900000
b10 I
11
1&
#10000000
01
0&
#10100000
b11 I
11
1&
#10200000
01
0&
#10300000
b100 I
11
1&
#10400000
01
0&
#10500000
b101 I
11
1&
#10600000
01
0&
#10700000
b110 I
11
1&
#10800000
01
0&
#10900000
b111 I
11
1&
#11000000
01
0&
#11100000
b1000 I
11
1&
#11200000
01
0&
#11300000
0H
0=
b0 I
11
1&
#11400000
01
0&
#11500000
b1 I
11
1&
#11600000
01
0&
#11700000
b10 I
11
1&
#11800000
01
0&
#11900000
b11 I
11
1&
#12000000
01
0&
#12100000
b100 I
11
1&
#12200000
01
0&
#12300000
b101 I
11
1&
#12400000
01
0&
#12500000
b110 I
11
1&
#12600000
01
0&
#12700000
b111 I
11
1&
#12800000
01
0&
#12900000
b1000 I
11
1&
#13000000
01
0&
#13100000
b1000 6
b11 4
b11 #
b11 7
b1000 K
b1000 "
b1000 2
b1000 >
b0 L
b11 M
b10 D
1H
1=
b0 I
11
1&
#13200000
01
0&
#13300000
b1 I
11
1&
#13400000
01
0&
#13500000
b10 I
11
1&
#13600000
01
0&
#13700000
b11 I
11
1&
#13800000
01
0&
#13900000
b100 I
11
1&
#14000000
01
0&
#14100000
b101 I
11
1&
#14200000
01
0&
#14300000
b110 I
11
1&
#14400000
01
0&
#14500000
b111 I
11
1&
#14600000
01
0&
#14700000
b1000 I
11
1&
#14800000
01
0&
#14900000
0H
0=
b0 I
11
1&
#15000000
01
0&
#15100000
b1 I
11
1&
#15200000
01
0&
#15300000
b10 I
11
1&
#15400000
01
0&
#15500000
b11 I
11
1&
#15600000
01
0&
#15700000
b100 I
11
1&
#15800000
01
0&
#15900000
b101 I
11
1&
#16000000
01
0&
#16100000
b110 I
11
1&
#16200000
01
0&
#16300000
b111 I
11
1&
#16400000
01
0&
#16500000
b1000 I
11
1&
#16600000
01
0&
#16700000
b1100001 8
b1100001 !
b1 6
b100 4
b100 #
b100 7
1J
1<
b1 K
b1 "
b1 2
b1 >
b1 L
b0 M
b1 D
1H
1=
b0 I
11
1&
#16800000
01
0&
#16900000
b1 I
11
1&
#17000000
01
0&
#17100000
b10 I
11
1&
#17200000
01
0&
#17300000
b11 I
11
1&
#17400000
01
0&
#17500000
b100 I
11
1&
#17600000
01
0&
#17700000
b101 I
11
1&
#17800000
01
0&
#17900000
b110 I
11
1&
#18000000
01
0&
#18100000
b111 I
11
1&
#18200000
01
0&
#18300000
b1000 I
11
1&
#18400000
01
0&
#18500000
0H
0=
b0 I
11
1&
#18600000
01
0&
#18700000
b1 I
11
1&
#18800000
01
0&
#18900000
b10 I
11
1&
#19000000
01
0&
#19100000
b11 I
11
1&
#19200000
01
0&
#19300000
b100 I
11
1&
#19400000
01
0&
#19500000
b101 I
11
1&
#19600000
01
0&
#19700000
b110 I
11
1&
#19800000
01
0&
#19900000
b111 I
11
1&
#20000000
01
0&
#20100000
b1000 I
11
1&
#20200000
01
0&
#20300000
b1 M
0J
0<
b0 K
b0 "
b0 2
b0 >
b1 L
0?
b0 D
1$
1H
1=
b0 I
11
1&
#20400000
01
0&
